thinkml/__init__.py
thinkml/algorithms/__init__.py
thinkml/algorithms/adaboost.py
thinkml/algorithms/advanced_classification.py
thinkml/algorithms/advanced_regression.py
thinkml/algorithms/base.py
thinkml/algorithms/decision_tree.py
thinkml/algorithms/gradient_boosting.py
thinkml/algorithms/knn.py
thinkml/algorithms/lasso_regression.py
thinkml/algorithms/linear.py
thinkml/algorithms/linear_regression.py
thinkml/algorithms/logistic_regression.py
thinkml/algorithms/neural_network.py
thinkml/algorithms/random_forest.py
thinkml/algorithms/ridge_regression.py
thinkml/algorithms/svm.py
thinkml/algorithms/tree.py
thinkml/analyzer/__init__.py
thinkml/analyzer/model_suggester.py
thinkml/automl/__init__.py
thinkml/automl/pipeline.py
thinkml/calibration/__init__.py
thinkml/calibration/calibrator.py
thinkml/calibration/probability_calibration.py
thinkml/classification/__init__.py
thinkml/classification/advanced_classification.py
thinkml/classification/cost_sensitive.py
thinkml/classification/multi_label.py
thinkml/classification/ordinal_classification.py
thinkml/data_analysis/__init__.py
thinkml/data_analysis/describe.py
thinkml/data_split/__init__.py
thinkml/data_split/splitter.py
thinkml/describer/data_describer.py
thinkml/eda/__init__.py
thinkml/eda/plot.py
thinkml/evaluation/__init__.py
thinkml/evaluation/evaluator.py
thinkml/evaluation/metrics.py
thinkml/feature_engineering/__init__.py
thinkml/feature_engineering/feature_creation.py
thinkml/feature_engineering/feature_creator.py
thinkml/feature_engineering/feature_engineer.py
thinkml/feature_engineering/feature_engineering.py
thinkml/feature_engineering/feature_selection.py
thinkml/feature_engineering/feature_transformer.py
thinkml/feature_selection/__init__.py
thinkml/feature_selection/selector.py
thinkml/helpers/notebook_helper.py
thinkml/helpers/user_interface.py
thinkml/hyperparameter_tuning/__init__.py
thinkml/inspector/__init__.py
thinkml/inspector/inspector.py
thinkml/interpretability/__init__.py
thinkml-1.0.1.dist-info/LICENSE
thinkml-1.0.1.dist-info/METADATA
thinkml-1.0.1.dist-info/WHEEL
thinkml-1.0.1.dist-info/top_level.txt
thinkml-1.0.1.dist-info/RECORD
