Metadata-Version: 2.1
Name: thinkml
Version: 1.0.1
Summary: End-to-End Machine Learning Workflow Library
Home-page: https://github.com/ArpanChaudhary/ThinkML
Author: Arpan Chaudhary
Author-email: arpanchaudhary@gmail.com
License: UNKNOWN
Project-URL: Bug Tracker, https://github.com/ArpanChaudhary/ThinkML/issues
Project-URL: Documentation, https://github.com/ArpanChaudhary/ThinkML#readme
Project-URL: Source Code, https://github.com/ArpanChaudhary/ThinkML
Platform: UNKNOWN
Classifier: Development Status :: 4 - Beta
Classifier: Intended Audience :: Science/Research
Classifier: License :: OSI Approved :: MIT License
Classifier: Programming Language :: Python :: 3
Classifier: Programming Language :: Python :: 3.8
Classifier: Programming Language :: Python :: 3.9
Classifier: Programming Language :: Python :: 3.10
Classifier: Topic :: Scientific/Engineering :: Artificial Intelligence
Classifier: Operating System :: OS Independent
Requires-Python: >=3.8
License-File: LICENSE
Requires-Dist: numpy>=1.20.0
Requires-Dist: pandas>=1.3.0
Requires-Dist: scikit-learn>=1.0.0
Requires-Dist: dask>=2023.1.0
Requires-Dist: matplotlib>=3.4.0
Requires-Dist: seaborn>=0.11.0
Requires-Dist: plotly>=5.0.0
Requires-Dist: xgboost>=1.5.0
Requires-Dist: lightgbm>=3.3.0
Requires-Dist: catboost>=1.0.0; platform_system != "Windows"
